arbmaster/__init__.py
arbmaster/calc.py
arbmaster/client.py
arbmaster/constants.py
arbmaster/ext.py
arbmaster/logger.py
arbmaster-0.1.4.dist-info/LICENCE
arbmaster-0.1.4.dist-info/METADATA
arbmaster-0.1.4.dist-info/WHEEL
arbmaster-0.1.4.dist-info/top_level.txt
arbmaster-0.1.4.dist-info/RECORD
