Metadata-Version: 2.1
Name: arbmaster
Version: 0.1.4
Summary: Odds api automated arbitrage calculator
Author: Rashoo18
License: MIT License
Project-URL: Homepage, https://github.com/Rashoo18/arbmaster
Project-URL: Issues, https://github.com/Rashoo18/arbmaster/issues
Classifier: Programming Language :: Python :: 3
Classifier: License :: OSI Approved :: MIT License
Classifier: Operating System :: OS Independent
Requires-Python: >=3.8
License-File: LICENCE
Requires-Dist: requests-cache
Requires-Dist: colorlog
